[
  {
    "id": "71d6bcd-bbfd-4b2d-9b5d-ab8dfbbd4b71",
    "name": "Heaven Vienna",
    "description": "One of Vienna's most glamorous queer event brands, renowned for legendary LGBTQ+ parties at stylish venues. Popular among the younger crowd with themed parties and vibrant dance floors. One of the longest running gay club nights in Vienna.",
    "website": null,
    "address": "Various locations",
    "city": "Vienna",
    "country": "Austria",
    "latitude": 48.2082,
    "longitude": 16.3738,
    "banner_url": null,
    "opening_hours": "Saturday 22:00-06:00",
    "owner_id": null,
    "created_at": "2025-12-09T10:00:00Z",
    "updated_at": "2025-12-09T10:00:00Z"
  },
  {
    "id": "72d6bcd-bbfd-4b2d-9b5d-ab8dfbbd4b72",
    "name": "Heidi – Das Chalet am Ring",
    "description": "Champagne club in Vienna's first district featuring chalet-style décor. Opened March 2022. Located at Opernring with capacity for up to 500 people for exclusive events. Open primarily on weekend nights.",
    "website": "https://www.instagram.com/heidi.vienna",
    "address": "Opernring 11",
    "city": "Vienna",
    "country": "Austria",
    "latitude": 48.2018,
    "longitude": 16.3689,
    "banner_url": null,
    "opening_hours": "Primarily Friday and Saturday nights",
    "owner_id": null,
    "created_at": "2025-12-09T10:00:00Z",
    "updated_at": "2025-12-09T10:00:00Z"
  },
  {
    "id": "73d6bcd-bbfd-4b2d-9b5d-ab8dfbbd4b73",
    "name": "Inc.",
    "description": "Hip-hop club located at Schwarzenbergplatz, formerly known as Club Schwarzenberg. Part of the Horst Group. Features electronic and hip-hop music across multiple floors with regular DJ events and themed parties.",
    "website": "https://www.inc.wien",
    "address": "Schwarzenbergplatz 7",
    "city": "Vienna",
    "country": "Austria",
    "latitude": 48.1995,
    "longitude": 16.3767,
    "banner_url": null,
    "opening_hours": "Tue 23:00-06:00, Thu-Sat 23:00-06:00, Closed Wed, Sun, Mon",
    "owner_id": null,
    "created_at": "2025-12-09T10:00:00Z",
    "updated_at": "2025-12-09T10:00:00Z"
  },
  {
    "id": "74d6bcd-bbfd-4b2d-9b5d-ab8dfbbd4b74",
    "name": "Jazzland",
    "description": "Vienna's oldest jazz club in rustic cellar under Ruprechtskirche. Operating since 1972. Features live jazz performances in three sets from 21:00-01:00. Cash only venue with intimate atmosphere.",
    "website": "https://www.jazzland.at",
    "address": "Franz-Josefs-Kai 29",
    "city": "Vienna",
    "country": "Austria",
    "latitude": 48.2148,
    "longitude": 16.3747,
    "banner_url": null,
    "opening_hours": "Mon-Sat 19:00-04:00, Sun Closed",
    "owner_id": null,
    "created_at": "2025-12-09T10:00:00Z",
    "updated_at": "2025-12-09T10:00:00Z"
  },
  {
    "id": "75d6bcd-bbfd-4b2d-9b5d-ab8dfbbd4b75",
    "name": "Ken Club",
    "description": "Vibrant roaming dance party event in Vienna drawing energetic crowds of young gays, lesbians, and friends. Features dynamic playlist spanning pop, trash, 80s, 90s, and house music. Venues and schedules vary by event.",
    "website": "https://www.kenclub.at",
    "address": "Various locations",
    "city": "Vienna",
    "country": "Austria",
    "latitude": 48.2082,
    "longitude": 16.3738,
    "banner_url": null,
    "opening_hours": "Event-based, check website",
    "owner_id": null,
    "created_at": "2025-12-09T10:00:00Z",
    "updated_at": "2025-12-09T10:00:00Z"
  },
  {
    "id": "76d6bcd-bbfd-4b2d-9b5d-ab8dfbbd4b76",
    "name": "Kleinod Stadtgarten",
    "description": "Exquisite dining and bar experience in beautiful garden setting at the entrance of Stadtpark in Vienna's city center. Features outdoor seating in scenic location with quality food and drinks.",
    "website": "https://kleinod-stadtgarten.wien",
    "address": "Johannesgasse 33",
    "city": "Vienna",
    "country": "Austria",
    "latitude": 48.2034,
    "longitude": 16.3789,
    "banner_url": null,
    "opening_hours": "Daily 12:00-00:00",
    "owner_id": null,
    "created_at": "2025-12-09T10:00:00Z",
    "updated_at": "2025-12-09T10:00:00Z"
  },
  {
    "id": "77d6bcd-bbfd-4b2d-9b5d-ab8dfbbd4b77",
    "name": "Kramladen",
    "description": "Leading venue in Vienna's underground music scene since 2015. Set within unique underground arches (U-Bahnbogen), featuring live concerts across various genres including electronic, rock, and indie music. Hosts thousands of alternative events.",
    "website": "https://www.kramladenvienna.at",
    "address": "U-Bahnbogen 39-40",
    "city": "Vienna",
    "country": "Austria",
    "latitude": 48.2189,
    "longitude": 16.3401,
    "banner_url": null,
    "opening_hours": "Mon-Tue 20:00-04:00, Wed-Sat 20:00-06:00",
    "owner_id": null,
    "created_at": "2025-12-09T10:00:00Z",
    "updated_at": "2025-12-09T10:00:00Z"
  },
  {
    "id": "78d6bcd-bbfd-4b2d-9b5d-ab8dfbbd4b78",
    "name": "Krypt",
    "description": "Historic vaulted cellar bar with alleged past as semi-legal jazz club in the 1950s/1960s. Features speakeasy theme with hidden bar behind vending machine. Stylish modern cocktail bar with mystical glamour atmosphere.",
    "website": "https://www.krypt.bar",
    "address": "Wasagasse 17",
    "city": "Vienna",
    "country": "Austria",
    "latitude": 48.2178,
    "longitude": 16.3567,
    "banner_url": null,
    "opening_hours": "Wed-Sat 21:00-02:00, Sun-Tue Closed",
    "owner_id": null,
    "created_at": "2025-12-09T10:00:00Z",
    "updated_at": "2025-12-09T10:00:00Z"
  },
  {
    "id": "79d6bcd-bbfd-4b2d-9b5d-ab8dfbbd4b79",
    "name": "Loco Bar",
    "description": "Lively bar in U-Bahn arches known for karaoke nights on Wednesdays. Features happy hour from 19:00-20:00 with special cocktail prices. Open daily with extended hours on weekends.",
    "website": "https://www.locobar.at",
    "address": "Währinger Gürtel 172-174",
    "city": "Vienna",
    "country": "Austria",
    "latitude": 48.2289,
    "longitude": 16.3567,
    "banner_url": null,
    "opening_hours": "Daily from 19:00, Sun-Thu until 04:00, Fri-Sat until 05:00",
    "owner_id": null,
    "created_at": "2025-12-09T10:00:00Z",
    "updated_at": "2025-12-09T10:00:00Z"
  },
  {
    "id": "80d6bcd-bbfd-4b2d-9b5d-ab8dfbbd4b80",
    "name": "Loop",
    "description": "Popular cocktail bar and meeting place for music lovers under the U6 subway (Thaliastrasse stop). Features live music, DJ sets, and cozy atmosphere. Part of Vienna's vibrant Gürtel nightlife scene with moderate prices.",
    "website": "https://loop.co.at",
    "address": "Lerchenfelder Gürtel 26-27",
    "city": "Vienna",
    "country": "Austria",
    "latitude": 48.2156,
    "longitude": 16.3423,
    "banner_url": null,
    "opening_hours": "Mon-Thu 19:00-02:00, Fri-Sat 19:00-04:00, Sun 19:00-01:00",
    "owner_id": null,
    "created_at": "2025-12-09T10:00:00Z",
    "updated_at": "2025-12-09T10:00:00Z"
  }
]
